paravastu/__init__.py
paravastu-1.21.dist-info/METADATA
paravastu-1.21.dist-info/WHEEL
paravastu-1.21.dist-info/top_level.txt
paravastu-1.21.dist-info/RECORD
