Metadata-Version: 2.1
Name: paravastu
Version: 1.21
Summary: UNKNOWN
Home-page: UNKNOWN
Author: Paravastu Lab
License: UNKNOWN
Platform: UNKNOWN
Requires-Python: >=3.6
Requires-Dist: numpy
Requires-Dist: pandas
Requires-Dist: biopandas
Requires-Dist: dtale
Requires-Dist: plotnine
